oceana_token/__init__.py
oceana_token/authenticate.py
oceana_token/exceptions.py
oceana_token/utils.py
oceana_token-0.0.4.dist-info/METADATA
oceana_token-0.0.4.dist-info/WHEEL
oceana_token-0.0.4.dist-info/top_level.txt
oceana_token-0.0.4.dist-info/RECORD
