Metadata-Version: 2.1
Name: oceana_token
Version: 0.0.4
Summary: Oceana API library to manage authentication token and headers
Author: jorgegilramos
License: License :: OSI Approved :: MIT License
Classifier: Programming Language :: Python :: 3
Classifier: License :: OSI Approved :: MIT License
Classifier: Operating System :: OS Independent
Requires-Dist: build>=1.2.1
Requires-Dist: setuptools~=67.8.0
Requires-Dist: wheel~=0.38.4
Requires-Dist: requests>=2.29.0
Requires-Dist: python-decouple>=3.8
Requires-Dist: typing-extensions~=4.12.2
Requires-Dist: requests-mock>=1.12.1
Requires-Dist: pyjwt>=2.8.0
Requires-Dist: pytest>=7.4.0
Requires-Dist: coverage>=6.4.4
Requires-Dist: flake8>=4.0.1
